__init__.py
slider_captcha_match.py
slider_captcha_match-1.0.5.dist-info/METADATA
slider_captcha_match-1.0.5.dist-info/WHEEL
slider_captcha_match-1.0.5.dist-info/entry_points.txt
slider_captcha_match-1.0.5.dist-info/RECORD
