Metadata-Version: 2.1
Name: slider-captcha-match
Version: 1.0.5
Summary: Slider Captcha Match 是一个基于 Python 和 OpenCV 的滑块验证码匹配工具，旨在通过对比滑块和背景图像来计算滑块的正确偏移量。该项目主要用于验证图像处理和匹配算法。
License: Apache-2.0
Author: ityangs
Author-email: ityangs@163.com
Requires-Python: >=3.8,<4.0
Classifier: License :: OSI Approved :: Apache Software License
Classifier: Programming Language :: Python :: 3
Classifier: Programming Language :: Python :: 3.8
Classifier: Programming Language :: Python :: 3.9
Classifier: Programming Language :: Python :: 3.10
Classifier: Programming Language :: Python :: 3.11
Classifier: Programming Language :: Python :: 3.12
Requires-Dist: numpy (>=1.21,<2.0)
Requires-Dist: opencv-python (>=4.5,<5.0)
